jp_prefecture/__init__.py
jp_prefecture/address.py
jp_prefecture/checkdigit.py
jp_prefecture/immutable_dict.py
jp_prefecture/jp_cities.py
jp_prefecture/jp_numbers.py
jp_prefecture/jp_prefecture.py
jp_prefecture/singledispatchmethod.py
jp_prefecture/utils.py
jp_prefecture/versions.py
jp_prefecture/data/cities.csv
jp_prefecture/data/towns.csv
jp_prefecture-0.7.9.1.dist-info/LICENSE
jp_prefecture-0.7.9.1.dist-info/METADATA
jp_prefecture-0.7.9.1.dist-info/WHEEL
jp_prefecture-0.7.9.1.dist-info/top_level.txt
jp_prefecture-0.7.9.1.dist-info/RECORD
