Metadata-Version: 2.1
Name: jp-prefecture
Version: 0.7.9.1
Summary: Simple utilitiy convert name of japanese prefectures
Home-page: https://github.com/iisaka51/jp_prefecture
Author: iisaka51
Author-email: iisaka51@gmail.com
License: MIT
Platform: UNKNOWN
Classifier: License :: OSI Approved :: MIT License
Classifier: Programming Language :: Python :: 3.10
License-File: LICENSE
Requires-Dist: pandas
